tests/__init__.py
tests/threatbutt_test.py
threatbutt/__init__.py
threatbutt/MaltegoTransform.py
threatbutt/threatbutt.py
threatbutt-1.0.8.dist-info/DESCRIPTION.rst
threatbutt-1.0.8.dist-info/entry_points.txt
threatbutt-1.0.8.dist-info/METADATA
threatbutt-1.0.8.dist-info/metadata.json
threatbutt-1.0.8.dist-info/RECORD
threatbutt-1.0.8.dist-info/top_level.txt
threatbutt-1.0.8.dist-info/WHEEL
