Metadata-Version: 2.0
Name: threatbutt
Version: 1.0.8
Summary: Defense in derpth - maximum protection from hacker threats like 4Chan and Reddit.
Home-page: https://github.com/ivanlei/threatbutt
Author: c0wl
Author-email: ivanlei@yelp.com
License: Apache License v 2.0
Platform: UNKNOWN
Provides: threatbutt
Requires-Dist: argparse (==1.3.0)
Requires-Dist: requests (==2.6.2)
